nitime/LICENSE
nitime/__init__.py
nitime/_compat.py
nitime/_utils.c
nitime/_utils.cpython-310-x86_64-linux-gnu.so
nitime/_utils.pyx
nitime/_version.py
nitime/conftest.py
nitime/descriptors.py
nitime/index_utils.py
nitime/lazy.py
nitime/lazyimports.py
nitime/timeseries.py
nitime/utils.py
nitime/viz.py
nitime/algorithms/__init__.py
nitime/algorithms/autoregressive.py
nitime/algorithms/cohere.py
nitime/algorithms/correlation.py
nitime/algorithms/entropy.py
nitime/algorithms/event_related.py
nitime/algorithms/filter.py
nitime/algorithms/spectral.py
nitime/algorithms/wavelet.py
nitime/algorithms/tests/__init__.py
nitime/algorithms/tests/test_autoregressive.py
nitime/algorithms/tests/test_coherence.py
nitime/algorithms/tests/test_correlation.py
nitime/algorithms/tests/test_entropy.py
nitime/algorithms/tests/test_event_related.py
nitime/algorithms/tests/test_spectral.py
nitime/analysis/__init__.py
nitime/analysis/base.py
nitime/analysis/coherence.py
nitime/analysis/correlation.py
nitime/analysis/event_related.py
nitime/analysis/granger.py
nitime/analysis/normalization.py
nitime/analysis/snr.py
nitime/analysis/spectral.py
nitime/analysis/tests/__init__.py
nitime/analysis/tests/test_base.py
nitime/analysis/tests/test_coherence.py
nitime/analysis/tests/test_correlation.py
nitime/analysis/tests/test_granger.py
nitime/analysis/tests/test_snr.py
nitime/data/event_related_fmri.csv
nitime/data/fmri1.nii.gz
nitime/data/fmri2.nii.gz
nitime/data/fmri_timeseries.csv
nitime/data/grasshopper_spike_times1.txt
nitime/data/grasshopper_spike_times2.txt
nitime/data/grasshopper_stimulus1.txt
nitime/data/grasshopper_stimulus2.txt
nitime/fmri/__init__.py
nitime/fmri/hrf.py
nitime/fmri/io.py
nitime/fmri/tests/__init__.py
nitime/fmri/tests/test_io.py
nitime/tests/__init__.py
nitime/tests/cxy_matlab.txt
nitime/tests/dpss_matlab.txt
nitime/tests/fxx_matlab.txt
nitime/tests/long_dpss_matlab.npy
nitime/tests/test_algorithms.py
nitime-0.12.1.dist-info/METADATA
nitime-0.12.1.dist-info/WHEEL
nitime-0.12.1.dist-info/top_level.txt
nitime-0.12.1.dist-info/RECORD
nitime-0.12.1.dist-info/licenses/LICENSE
