Metadata-Version: 2.4
Name: nitime
Version: 0.12.1
Summary: Nitime: timeseries analysis for neuroscience data
Author-email: Nitime developers <neuroimaging@python.org>
Maintainer-email: Nipy Developers <neuroimaging@python.org>
License: Copyright (c) 2006-2011, NIPY Developers
Project-URL: Download, http://github.com/nipy/nitime/downloads
Project-URL: Homepage, http://nipy.org/nitime
Classifier: Development Status :: 3 - Alpha
Classifier: Environment :: Console
Classifier: Intended Audience :: Science/Research
Classifier: License :: OSI Approved :: BSD License
Classifier: Operating System :: OS Independent
Classifier: Programming Language :: Python
Classifier: Topic :: Scientific/Engineering
Requires-Python: >=3.10
License-File: LICENSE
Requires-Dist: matplotlib>=3.7
Requires-Dist: numpy>=1.24
Requires-Dist: scipy>=1.10
Provides-Extra: full
Requires-Dist: networkx>=3.0; extra == "full"
Requires-Dist: nibabel>=5.0; extra == "full"
Dynamic: license-file
